japanize_matplotlib_jlite/__init__.py
japanize_matplotlib_jlite/japanize_matplotlib_jlite.py
japanize_matplotlib_jlite/fonts/IPA_Font_License_Agreement_v1.0.txt
japanize_matplotlib_jlite/fonts/Readme_ipaexg00301.txt
japanize_matplotlib_jlite/fonts/ipaexg.ttf
japanize_matplotlib_jlite-0.1.5.dist-info/LICENSE
japanize_matplotlib_jlite-0.1.5.dist-info/METADATA
japanize_matplotlib_jlite-0.1.5.dist-info/WHEEL
japanize_matplotlib_jlite-0.1.5.dist-info/top_level.txt
japanize_matplotlib_jlite-0.1.5.dist-info/RECORD
