Metadata-Version: 2.1
Name: japanize-matplotlib-jlite
Version: 0.1.5
Summary: JupyterLiteでmatplotlibのフォント設定を自動で日本語化する
Home-page: https://github.com/spring-haru/japanize-matplotlib-jlite
Author: spring-haru
Author-email: tetsu.yes@gmail.com
License: MIT License
License-File: LICENSE
Requires-Dist: matplotlib
